wordybin/__init__.py
wordybin/__main__.py
wordybin/_backward.py
wordybin/code.py
wordybin/py.typed
wordybin/words/512.txt
wordybin/words/threes.txt
wordybin-0.2.0.dist-info/LICENSE
wordybin-0.2.0.dist-info/METADATA
wordybin-0.2.0.dist-info/WHEEL
wordybin-0.2.0.dist-info/entry_points.txt
wordybin-0.2.0.dist-info/RECORD
