Metadata-Version: 2.1
Name: wordybin
Version: 0.2.0
Summary: Memorable word-based encoding for binary data.
Home-page: https://github.com/petergaultney/wordybin/
License: MIT
Author: Peter Gaultney
Author-email: petergaultney@gmail.com
Requires-Python: >=3.8,<4.0
Classifier: License :: OSI Approved :: MIT License
Classifier: Programming Language :: Python :: 3
Classifier: Programming Language :: Python :: 3.8
Classifier: Programming Language :: Python :: 3.9
Classifier: Programming Language :: Python :: 3.10
Classifier: Programming Language :: Python :: 3.11
Project-URL: Repository, https://github.com/petergaultney/wordybin/
